README.md
setup.cfg
setup.py
AdvPyProjectMN_1.egg-info/PKG-INFO
AdvPyProjectMN_1.egg-info/SOURCES.txt
AdvPyProjectMN_1.egg-info/dependency_links.txt
AdvPyProjectMN_1.egg-info/requires.txt
AdvPyProjectMN_1.egg-info/top_level.txt
mypackage/__init__.py
mypackage/mymodule.py
mypackage/template.txt